src/config_table/config_table.v
`timescale 1ns / 1ps

// Tabela de Configuração para o Canny APS
//
// ROM de 56 palavras × 34 bits, inicializada a partir de config_table.mem
// gerado pelo script scripts/generate_config_table.py.
//
// Endereçamento (6 bits):
//   addr = {noise_level[3:0], mdp[1:0]}
//   noise_level: 0 = 5%, 1 = 10%, ..., 13 = 70%  (saída do noise_estimator)
//   mdp:         0 = 91%, 1 = 92%, 2 = 93%, 3 = 94%
//
// Formato de cada palavra:
//   [33:32] kernel_sel  — selecciona o kernel Gaussiano
//                         00 = σ=0.9 (5×5), 01 = σ=1.1 (5×5)
//                         10 = σ=1.3 (7×7), 11 = σ=1.5 (7×7)
//   [31:16] th_high     — TH_H em ponto fixo Q0.16
//   [15:0]  th_low      — TH_L em ponto fixo Q0.16

module config_table (
    input  wire        clk,
    input  wire [3:0]  noise_level,   // Do noise_estimator (0–13)
    input  wire [1:0]  mdp,           // Nível MDP (0=91%, 1=92%, 2=93%, 3=94%)

    output wire [1:0]  kernel_sel,    // Selecção do kernel Gaussiano
    output wire [15:0] th_high,       // Limiar superior (TH_H) em Q0.16
    output wire [15:0] th_low         // Limiar inferior (TH_L) em Q0.16
);

    // ========================================================================
    // 1. MEMÓRIA ROM (56 palavras × 34 bits)
    // ========================================================================
    reg [33:0] rom [0:55];

    initial begin
        $readmemh("config_table.mem", rom);
    end

    // ========================================================================
    // 2. CÁLCULO DO ENDEREÇO
    // ========================================================================
    wire [5:0] addr;

    // Saturação: noise_level > 13 é tratado como 13
    wire [3:0] noise_clamped = (noise_level > 4'd13) ? 4'd13 : noise_level;

    assign addr = {noise_clamped, mdp};

    // ========================================================================
    // 3. LEITURA SÍNCRONA
    // ========================================================================
    reg [33:0] rom_data;

    always @(posedge clk) begin
        rom_data <= rom[addr];
    end

    // ========================================================================
    // 4. DECOMPOSIÇÃO DA PALAVRA
    // ========================================================================
    assign kernel_sel = rom_data[33:32];
    assign th_high    = rom_data[31:16];
    assign th_low     = rom_data[15:0];

endmodule

src/config_table/tb_config_table.v
`timescale 1ns / 1ps

// iverilog -g2001 -o sim_config_table.out tb_config_table.v config_table.v
module tb_config_table;

    reg         clk;
    reg  [3:0]  noise_level;
    reg  [1:0]  mdp;
    wire [1:0]  kernel_sel;
    wire [15:0] th_high;
    wire [15:0] th_low;

    integer error_count;

    config_table #(
        .MEM_FILE("config_table.mem")
    ) dut (
        .clk         (clk),
        .noise_level (noise_level),
        .mdp         (mdp),
        .kernel_sel  (kernel_sel),
        .th_high     (th_high),
        .th_low      (th_low)
    );

    initial clk = 1'b0;
    always #5 clk = ~clk;

    task read_and_display;
        input [3:0] n;
        input [1:0] m;
        begin
            noise_level = n;
            mdp         = m;
            @(posedge clk);
            @(posedge clk);
            #1;
            $display("  N=%2d%% MDP=%0d%% → kernel_sel=%0d  TH_H=0x%04X (%.4f)  TH_L=0x%04X (%.4f)",
                (n + 1) * 5,
                91 + m,
                kernel_sel,
                th_high, th_high / 65536.0,
                th_low,  th_low  / 65536.0);
        end
    endtask

    initial begin
        $dumpfile("onda_config_table.vcd");
        $dumpvars(0, tb_config_table);

        $display("==================================================");
        $display("Teste da Tabela de Configuracao APS");
        $display("==================================================");

        error_count = 0;
        noise_level = 4'd0;
        mdp         = 2'd0;
        #20;

        // --------------------------------------------------------
        // TESTE 1: Verificar a primeira entrada (N=5%, MDP=91%)
        // Da Table 4: σ=0.9, TH_H=0.25
        // kernel_sel=0 (σ=0.9), th_high=0x4000, th_low=0x199A
        // --------------------------------------------------------
        $display("\n--- Teste 1: Entradas de canto ---");
        noise_level = 4'd0;
        mdp         = 2'd0;
        @(posedge clk);
        @(posedge clk);
        #1;

        if (kernel_sel !== 2'd0) begin
            $display("[ERRO] N=5%% MDP=91%%: kernel_sel esperado=0, obtido=%0d", kernel_sel);
            error_count = error_count + 1;
        end else begin
            $display("[OK]   N=5%% MDP=91%%: kernel_sel=0 (sigma=0.9)");
        end

        // --------------------------------------------------------
        // TESTE 2: N=5%, MDP=94% → σ=1.3 → kernel_sel=2
        // --------------------------------------------------------
        noise_level = 4'd0;
        mdp         = 2'd3;
        @(posedge clk);
        @(posedge clk);
        #1;

        if (kernel_sel !== 2'd2) begin
            $display("[ERRO] N=5%% MDP=94%%: kernel_sel esperado=2, obtido=%0d", kernel_sel);
            error_count = error_count + 1;
        end else begin
            $display("[OK]   N=5%% MDP=94%%: kernel_sel=2 (sigma=1.3)");
        end

        // --------------------------------------------------------
        // TESTE 3: N=70%, MDP=94% → σ=1.5 → kernel_sel=3
        // --------------------------------------------------------
        noise_level = 4'd13;
        mdp         = 2'd3;
        @(posedge clk);
        @(posedge clk);
        #1;

        if (kernel_sel !== 2'd3) begin
            $display("[ERRO] N=70%% MDP=94%%: kernel_sel esperado=3, obtido=%0d", kernel_sel);
            error_count = error_count + 1;
        end else begin
            $display("[OK]   N=70%% MDP=94%%: kernel_sel=3 (sigma=1.5)");
        end

        // --------------------------------------------------------
        // TESTE 4: Saturação — noise_level=15 tratado como 13
        // --------------------------------------------------------
        noise_level = 4'd15;
        mdp         = 2'd0;
        @(posedge clk);
        @(posedge clk);
        #1;

        if (kernel_sel !== 2'd3) begin
            $display("[ERRO] Saturacao: kernel_sel esperado=3, obtido=%0d", kernel_sel);
            error_count = error_count + 1;
        end else begin
            $display("[OK]   Saturacao (noise=15→13): kernel_sel=3");
        end

        // --------------------------------------------------------
        // TESTE 5: Varrimento completo — imprimir todas as entradas
        // --------------------------------------------------------
        $display("\n--- Varrimento completo da tabela ---");

        read_and_display(4'd0,  2'd0);
        read_and_display(4'd0,  2'd1);
        read_and_display(4'd0,  2'd2);
        read_and_display(4'd0,  2'd3);
        read_and_display(4'd6,  2'd0);
        read_and_display(4'd6,  2'd3);
        read_and_display(4'd13, 2'd0);
        read_and_display(4'd13, 2'd3);

        // --------------------------------------------------------
        // TESTE 6: TH_L ≈ 0.4 × TH_H
        // --------------------------------------------------------
        $display("\n--- Teste 6: Relacao TH_L = 0.4 * TH_H ---");
        noise_level = 4'd3;
        mdp         = 2'd3;
        @(posedge clk);
        @(posedge clk);
        #1;
        begin : th_check
            reg [31:0] expected_thl;
            expected_thl = (th_high * 4) / 10;
            if (th_low > expected_thl + 2 || th_low + 2 < expected_thl) begin
                $display("[ERRO] TH_L=0x%04X nao corresponde a 0.4*TH_H=0x%04X (esperado ~0x%04X)",
                    th_low, th_high, expected_thl[15:0]);
                error_count = error_count + 1;
            end else begin
                $display("[OK]   TH_L=0x%04X ≈ 0.4 * TH_H=0x%04X", th_low, th_high);
            end
        end

        // ========================================================================
        $display("\n==================================================");
        if (error_count == 0) begin
            $display("SUCESSO! 0 erros encontrados.");
        end else begin
            $display("FALHA. Total de erros: %0d", error_count);
        end
        $display("==================================================");

        $finish;
    end

endmodule

onda_config_table.vcd
$date
	Sat Jun 27 11:13:25 2026
$end
$version
	Icarus Verilog
$end
$timescale
	1ps
$end
$scope module tb_config_table $end
$var wire 16 ! th_low [15:0] $end
$var wire 16 " th_high [15:0] $end
$var wire 2 # kernel_sel [1:0] $end
$var reg 1 $ clk $end
$var reg 2 % mdp [1:0] $end
$var reg 4 & noise_level [3:0] $end
$var integer 32 ' error_count [31:0] $end
$scope module dut $end
$var wire 1 $ clk $end
$var wire 2 ( mdp [1:0] $end
$var wire 4 ) noise_level [3:0] $end
$var wire 16 * th_low [15:0] $end
$var wire 16 + th_high [15:0] $end
$var wire 4 , noise_clamped [3:0] $end
$var wire 2 - kernel_sel [1:0] $end
$var wire 6 . addr [5:0] $end
$var reg 34 / rom_data [33:0] $end
$upscope $end
$scope begin th_check $end
$var reg 32 0 expected_thl [31:0] $end
$upscope $end
$scope task read_and_display $end
$var reg 2 1 m [1:0] $end
$var reg 4 2 n [3:0] $end
$upscope $end
$upscope $end
$enddefinitions $end
$comment Show the parameter values. $end
$dumpall
$end
#0
$dumpvars
bx 2
bx 1
bx 0
bx /
b0 .
bx -
b0 ,
bx +
bx *
b0 )
b0 (
b0 '
b0 &
b0 %
0$
bx #
bx "
bx !
$end
#5000
1$
#10000
0$
#15000
1$
#20000
0$
#25000
1$
#30000
0$
#35000
1$
#36000
b11 .
b11 %
b11 (
b1 '
#40000
0$
#45000
1$
#50000
0$
#55000
1$
#56000
b110111 .
b1101 ,
b1101 &
b1101 )
b10 '
#60000
0$
#65000
1$
#70000
0$
#75000
1$
#76000
b110100 .
b0 %
b0 (
b1111 &
b1111 )
b11 '
#80000
0$
#85000
1$
#90000
0$
#95000
1$
#96000
b0 .
b0 ,
b0 &
b0 )
b0 1
b0 2
b100 '
#100000
0$
#105000
1$
#110000
0$
#115000
1$
#116000
b1 .
b1 %
b1 (
b1 1
#120000
0$
#125000
1$
#130000
0$
#135000
1$
#136000
b10 .
b10 %
b10 (
b10 1
#140000
0$
#145000
1$
#150000
0$
#155000
1$
#156000
b11 .
b11 %
b11 (
b11 1
#160000
0$
#165000
1$
#170000
0$
#175000
1$
#176000
b110 ,
b11000 .
b0 %
b0 (
b110 &
b110 )
b0 1
b110 2
#180000
0$
#185000
1$
#190000
0$
#195000
1$
#196000
b11011 .
b11 %
b11 (
b11 1
#200000
0$
#205000
1$
#210000
0$
#215000
1$
#216000
b1101 ,
b110100 .
b0 %
b0 (
b1101 &
b1101 )
b0 1
b1101 2
#220000
0$
#225000
1$
#230000
0$
#235000
1$
#236000
b110111 .
b11 %
b11 (
b11 1
#240000
0$
#245000
1$
#250000
0$
#255000
1$
#256000
b1111 .
b11 ,
b11 &
b11 )
